entity_search_client/__init__.py
entity_search_client/_configuration.py
entity_search_client/_entity_search_client.py
entity_search_client/version.py
entity_search_client/aio/__init__.py
entity_search_client/aio/_configuration.py
entity_search_client/aio/_entity_search_client.py
entity_search_client/aio/operations/__init__.py
entity_search_client/aio/operations/_entities_operations.py
entity_search_client/models/__init__.py
entity_search_client/models/_entity_search_client_enums.py
entity_search_client/models/_models.py
entity_search_client/models/_models_py3.py
entity_search_client/operations/__init__.py
entity_search_client/operations/_entities_operations.py
microsoft_bing_entitysearch-1.0.0.dist-info/LICENSE.txt
microsoft_bing_entitysearch-1.0.0.dist-info/METADATA
microsoft_bing_entitysearch-1.0.0.dist-info/WHEEL
microsoft_bing_entitysearch-1.0.0.dist-info/top_level.txt
microsoft_bing_entitysearch-1.0.0.dist-info/RECORD
