Metadata-Version: 2.1
Name: microsoft-bing-entitysearch
Version: 1.0.0
Summary: Microsoft Bing Entity Search Client Library for Python
Home-page: https://github.com/Azure/azure-sdk-for-python
Author: Microsoft Corporation
Author-email: v-mariamal@microsoft.com
License: MIT License
Platform: UNKNOWN
Classifier: Development Status :: 4 - Beta
Classifier: Programming Language :: Python
Classifier: Programming Language :: Python :: 2
Classifier: Programming Language :: Python :: 2.7
Classifier: Programming Language :: Python :: 3
Classifier: Programming Language :: Python :: 3.5
Classifier: Programming Language :: Python :: 3.6
Classifier: Programming Language :: Python :: 3.7
Classifier: Programming Language :: Python :: 3.8
Classifier: License :: OSI Approved :: MIT License
Requires-Dist: msrest (>=0.5.0)
Requires-Dist: msrestazure (<2.0.0,>=0.4.32)
Requires-Dist: azure-common (~=1.1)
